groupdocs/__init__.py
groupdocs/metadata.cp310-win32.pyd
groupdocs/metadata.cp311-win32.pyd
groupdocs/metadata.cp35-win32.pyd
groupdocs/metadata.cp36-win32.pyd
groupdocs/metadata.cp37-win32.pyd
groupdocs/metadata.cp38-win32.pyd
groupdocs/metadata.cp39-win32.pyd
groupdocs/pycore.cp310-win32.pyd
groupdocs/pycore.cp311-win32.pyd
groupdocs/pycore.cp35-win32.pyd
groupdocs/pycore.cp36-win32.pyd
groupdocs/pycore.cp37-win32.pyd
groupdocs/pycore.cp38-win32.pyd
groupdocs/pycore.cp39-win32.pyd
groupdocs/pygc.cp310-win32.pyd
groupdocs/pygc.cp311-win32.pyd
groupdocs/pygc.cp35-win32.pyd
groupdocs/pygc.cp36-win32.pyd
groupdocs/pygc.cp37-win32.pyd
groupdocs/pygc.cp38-win32.pyd
groupdocs/pygc.cp39-win32.pyd
groupdocs/pyreflection.cp310-win32.pyd
groupdocs/pyreflection.cp311-win32.pyd
groupdocs/pyreflection.cp35-win32.pyd
groupdocs/pyreflection.cp36-win32.pyd
groupdocs/pyreflection.cp37-win32.pyd
groupdocs/pyreflection.cp38-win32.pyd
groupdocs/pyreflection.cp39-win32.pyd
groupdocs/__pyinstaller/__init__.pyi
groupdocs/__pyinstaller/hook-groupdocs.py
groupdocs/assemblies/metadata/GroupDocs.Metadata.dll
groupdocs/assemblies/metadata/Microsoft.Win32.SystemEvents.dll
groupdocs/assemblies/metadata/Newtonsoft.Json.dll
groupdocs/assemblies/metadata/SkiaSharp.dll
groupdocs/assemblies/metadata/System.CodeDom.dll
groupdocs/assemblies/metadata/System.Drawing.Common.dll
groupdocs/assemblies/metadata/System.Runtime.CompilerServices.Unsafe.dll
groupdocs/assemblies/metadata/System.Security.AccessControl.dll
groupdocs/assemblies/metadata/System.Security.Permissions.dll
groupdocs/assemblies/metadata/System.Security.Principal.Windows.dll
groupdocs/assemblies/metadata/System.Text.Encoding.CodePages.dll
groupdocs/assemblies/metadata/System.Text.Encodings.Web.dll
groupdocs/assemblies/metadata/System.Text.Json.dll
groupdocs/assemblies/metadata/System.Windows.Extensions.dll
groupdocs/assemblies/metadata/WrpInterop.GroupDocs.Metadata.dll
groupdocs/assemblies/metadata/libSkiaSharp.dll
GroupDocs.Metadata-1.0.dist-info/METADATA
GroupDocs.Metadata-1.0.dist-info/WHEEL
GroupDocs.Metadata-1.0.dist-info/entry_points.txt
GroupDocs.Metadata-1.0.dist-info/top_level.txt
GroupDocs.Metadata-1.0.dist-info/RECORD
